evm_extras/__init__.py
evm_extras/abc.py
evm_extras/exceptions.py
evm_extras/globals.py
evm_extras/tools.py
evm_extras/types.py
evm_extras-0.2.3.post1.dist-info/LICENSE
evm_extras-0.2.3.post1.dist-info/METADATA
evm_extras-0.2.3.post1.dist-info/WHEEL
evm_extras-0.2.3.post1.dist-info/RECORD
