Metadata-Version: 2.1
Name: evm_extras
Version: 0.2.3.post1
Summary: The package containing utilities to develop Web3-based projects
Home-page: https://github.com/CrocoFactory/evm-extras
License: MIT
Author: Alexey
Author-email: axbelenkov@gmail.com
Requires-Python: >=3.11,<4.0
Classifier: Development Status :: 4 - Beta
Classifier: Intended Audience :: Developers
Classifier: License :: OSI Approved :: MIT License
Classifier: Operating System :: MacOS
Classifier: Operating System :: Microsoft :: Windows
Classifier: Programming Language :: Python :: 3
Classifier: Programming Language :: Python :: 3.11
Classifier: Programming Language :: Python :: 3.12
Classifier: Programming Language :: Python :: 3 :: Only
Classifier: Topic :: Software Development :: Libraries :: Python Modules
Requires-Dist: evm-wallet (>=2.0.2,<3.0.0)
Requires-Dist: python-extras (>=0.1.6,<0.2.0)
Requires-Dist: web3 (>=6.12.0,<7.0.0)
Project-URL: Repository, https://github.com/CrocoFactory/evm-extras
